GeeksforgeeksEngineeringMathematicsLectureNotes/README.md
GeeksforgeeksEngineeringMathematicsLectureNotes/__init__.py
GeeksforgeeksEngineeringMathematicsLectureNotes/__main__.py
GeeksforgeeksEngineeringMathematicsLectureNotes/file.epub
GeeksforgeeksEngineeringMathematicsLectureNotes/index.html
GeeksforgeeksEngineeringMathematicsLectureNotes/css/__init__.py
GeeksforgeeksEngineeringMathematicsLectureNotes/css/annotations.css
GeeksforgeeksEngineeringMathematicsLectureNotes/css/main.css
GeeksforgeeksEngineeringMathematicsLectureNotes/css/normalize.css
GeeksforgeeksEngineeringMathematicsLectureNotes/css/popup.css
GeeksforgeeksEngineeringMathematicsLectureNotes/font/__init__.py
GeeksforgeeksEngineeringMathematicsLectureNotes/font/fontello.eot
GeeksforgeeksEngineeringMathematicsLectureNotes/font/fontello.svg
GeeksforgeeksEngineeringMathematicsLectureNotes/font/fontello.ttf
GeeksforgeeksEngineeringMathematicsLectureNotes/font/fontello.woff
GeeksforgeeksEngineeringMathematicsLectureNotes/img/__init__.py
GeeksforgeeksEngineeringMathematicsLectureNotes/img/annotator-glyph-sprite.png
GeeksforgeeksEngineeringMathematicsLectureNotes/img/annotator-icon-sprite.png
GeeksforgeeksEngineeringMathematicsLectureNotes/img/apple-touch-icon.png
GeeksforgeeksEngineeringMathematicsLectureNotes/img/cancelfullscreen.png
GeeksforgeeksEngineeringMathematicsLectureNotes/img/close.png
GeeksforgeeksEngineeringMathematicsLectureNotes/img/fullscreen.png
GeeksforgeeksEngineeringMathematicsLectureNotes/img/loader.gif
GeeksforgeeksEngineeringMathematicsLectureNotes/img/menu-icon.png
GeeksforgeeksEngineeringMathematicsLectureNotes/img/save.png
GeeksforgeeksEngineeringMathematicsLectureNotes/img/saved.png
GeeksforgeeksEngineeringMathematicsLectureNotes/img/settings-s.png
GeeksforgeeksEngineeringMathematicsLectureNotes/img/settings.png
GeeksforgeeksEngineeringMathematicsLectureNotes/img/star.png
GeeksforgeeksEngineeringMathematicsLectureNotes/js/__init__.py
geeksforgeeks_engineering_mathematics_lecture_notes-2024.3.3.0.dist-info/METADATA
geeksforgeeks_engineering_mathematics_lecture_notes-2024.3.3.0.dist-info/WHEEL
geeksforgeeks_engineering_mathematics_lecture_notes-2024.3.3.0.dist-info/entry_points.txt
geeksforgeeks_engineering_mathematics_lecture_notes-2024.3.3.0.dist-info/top_level.txt
geeksforgeeks_engineering_mathematics_lecture_notes-2024.3.3.0.dist-info/RECORD
